foodtrend_analyzer/__init__.py
foodtrend_analyzer/main.py
foodtrend_analyzer/prompts.py
foodtrend_analyzer-2025.12.21184951.dist-info/METADATA
foodtrend_analyzer-2025.12.21184951.dist-info/WHEEL
foodtrend_analyzer-2025.12.21184951.dist-info/top_level.txt
foodtrend_analyzer-2025.12.21184951.dist-info/RECORD
