Metadata-Version: 2.4
Name: foodtrend-analyzer
Version: 2025.12.21184951
Summary: Analyze and summarize food trends from text inputs, extracting key points and identifying patterns.
Author-email: foodtrend-analyzer <hi@eugene.plus>
License: MIT
Project-URL: Homepage, https://github.com/chigwell/foodtrend-analyzer
Requires-Python: >=3.9
Requires-Dist: langchain-llm7>=0.0.0
Requires-Dist: llmatch-messages>=0.0.0
Requires-Dist: langchain-core>=0.3.0
